AWPfizerTweet/AWPfizerTweet.py
AWPfizerTweet/__init__.py
AWPfizerTweet12092022-0.0.1.dist-info/METADATA
AWPfizerTweet12092022-0.0.1.dist-info/WHEEL
AWPfizerTweet12092022-0.0.1.dist-info/top_level.txt
AWPfizerTweet12092022-0.0.1.dist-info/RECORD
