Metadata-Version: 2.1
Name: AWPfizerTweet12092022
Version: 0.0.1
Summary: My second python package
Home-page: UNKNOWN
Author: Alex Walters
Author-email: <runsolidbuddy@gmail.com>
License: UNKNOWN
Keywords: python,second package
Platform: UNKNOWN
Classifier: Development Status :: 3 - Alpha
Classifier: Intended Audience :: Education
Classifier: Programming Language :: Python :: 2
Classifier: Programming Language :: Python :: 3
Classifier: Operating System :: MacOS :: MacOS X
Classifier: Operating System :: Microsoft :: Windows
